pywework/__init__.py
pywework/py2_wework.so
pywework/py3_wework.so
pywework-1.1.5.dist-info/LICENSE
pywework-1.1.5.dist-info/METADATA
pywework-1.1.5.dist-info/WHEEL
pywework-1.1.5.dist-info/top_level.txt
pywework-1.1.5.dist-info/RECORD
