Metadata-Version: 2.1
Name: pywework
Version: 1.1.5
Summary: A simple handy tool for wework text msg sending
Home-page: UNKNOWN
Author: dev
Author-email: dev@7758258.xyz
License: UNKNOWN
Platform: UNKNOWN
Classifier: License :: OSI Approved :: MIT License
Classifier: Operating System :: POSIX :: Linux
Requires-Python: >=2.7, !=3.0.*, !=3.1.*, !=3.2.*, !=3.3.*, !=3.4.*, !=3.5.*, <3.7
Requires-Dist: requests
